prevenger/__init__.py
prevenger/cache/__init__.py
prevenger/cli.py
prevenger/crypto/__init__.py
prevenger/gen/__init__.py
prevenger/inspector/__init__.py
prevenger/kit/__init__.py
prevenger/kit/bloomfilter_kit.py
prevenger/kit/captcha_kit.py
prevenger/kit/dfa_kit.py
prevenger/kit/http_kit.py
prevenger/kit/id_card_kit.py
prevenger/kit/image_kit.py
prevenger/kit/path_kit.py
prevenger/kit/qrcode_kit.py
prevenger/kit/rand_kit.py
prevenger/orm/__init__.py
prevenger/orm/smart_filter/__init__.py
prevenger/records/__init__.py
prevenger/str_kit/__init__.py
prevenger/str_kit/regex_kit.py
prevenger/str_kit/str_kit.py
prevenger/str_kit/validator_kit.py
prevenger/timer.py
prevenger/validator/__init__.py
prevenger-0.0.5.dist-info/entry_points.txt
prevenger-0.0.5.dist-info/WHEEL
prevenger-0.0.5.dist-info/METADATA
prevenger-0.0.5.dist-info/RECORD
