Metadata-Version: 2.1
Name: prevenger
Version: 0.0.5
Summary: final commom utils for prevengers
Home-page: https://github.com/twocucao/prevengers
License: UNKNOWN
Keywords: prevenger
Author: twocucao
Author-email: twocucao@gmail.com
Requires-Python: >=3.7,<4.0
Classifier: Programming Language :: Python :: 3
Classifier: Programming Language :: Python :: 3.7
Requires-Dist: click_completion (>=0.5.1,<0.6.0)
Requires-Dist: click_didyoumean (>=0.0.3,<0.0.4)
Requires-Dist: crayons (>=0.2.0,<0.3.0)
Requires-Dist: requests
Requires-Dist: sqlalchemy
Requires-Dist: werkzeug
Project-URL: Repository, https://github.com/twocucao/prevengers
